py3dsa
