Metadata-Version: 2.1
Name: py3dsa
Version: 0.3.0
Summary: Data Structures and Algorithms examples and implementations
Author: Harihar Rengan
Author-email: harihar.rengan@gmail.com
Classifier: Programming Language :: Python :: 3
Classifier: License :: OSI Approved :: MIT License
Classifier: Operating System :: OS Independent
Requires-Python: >=3.6
